{
  "Lionic": {
    "detected": 1693,
    "seen": 3974
  },
  "CTX": {
    "detected": 2309,
    "seen": 3973
  },
  "huorong": {
    "detected": 2284,
    "seen": 3973
  },
  "VirIT": {
    "detected": 950,
    "seen": 3975
  },
  "ESET-NOD32": {
    "detected": 3053,
    "seen": 3975
  },
  "Cynet": {
    "detected": 2326,
    "seen": 3975
  },
  "ViRobot": {
    "detected": 430,
    "seen": 3975
  },
  "F-Secure": {
    "detected": 1938,
    "seen": 3975
  },
  "DrWeb": {
    "detected": 2053,
    "seen": 3975
  },
  "McAfeeD": {
    "detected": 2564,
    "seen": 3973
  },
  "Ikarus": {
    "detected": 2211,
    "seen": 3975
  },
  "Avira": {
    "detected": 1915,
    "seen": 3975
  },
  "GData": {
    "detected": 2357,
    "seen": 3975
  },
  "AhnLab-V3": {
    "detected": 2057,
    "seen": 3975
  },
  "TACHYON": {
    "detected": 94,
    "seen": 3975
  },
  "Zoner": {
    "detected": 138,
    "seen": 3975
  },
  "Tencent": {
    "detected": 2470,
    "seen": 3751
  },
  "SentinelOne": {
    "detected": 1956,
    "seen": 3975
  },
  "alibabacloud": {
    "detected": 2037,
    "seen": 3974
  },
  "Bkav": {
    "detected": 1673,
    "seen": 3942
  },
  "MicroWorld-eScan": {
    "detected": 2213,
    "seen": 3975
  },
  "ALYac": {
    "detected": 1791,
    "seen": 3540
  },
  "Malwarebytes": {
    "detected": 1608,
    "seen": 3975
  },
  "K7AntiVirus": {
    "detected": 1347,
    "seen": 3975
  },
  "K7GW": {
    "detected": 1400,
    "seen": 3975
  },
  "CrowdStrike": {
    "detected": 1769,
    "seen": 3975
  },
  "Microsoft": {
    "detected": 3270,
    "seen": 3975
  },
  "NANO-Antivirus": {
    "detected": 537,
    "seen": 3975
  },
  "Rising": {
    "detected": 2745,
    "seen": 3975
  },
  "VIPRE": {
    "detected": 2155,
    "seen": 3970
  },
  "Emsisoft": {
    "detected": 2237,
    "seen": 3975
  },
  "Jiangmin": {
    "detected": 570,
    "seen": 3975
  },
  "Antiy-AVL": {
    "detected": 2356,
    "seen": 3975
  },
  "Kingsoft": {
    "detected": 1542,
    "seen": 3974
  },
  "Gridinsoft": {
    "detected": 912,
    "seen": 3794
  },
  "Arcabit": {
    "detected": 2218,
    "seen": 3975
  },
  "SUPERAntiSpyware": {
    "detected": 270,
    "seen": 3975
  },
  "ZoneAlarm": {
    "detected": 1023,
    "seen": 3962
  },
  "Google": {
    "detected": 2937,
    "seen": 3975
  },
  "Acronis": {
    "detected": 27,
    "seen": 3975
  },
  "MaxSecure": {
    "detected": 1351,
    "seen": 3971
  },
  "Elastic": {
    "detected": 2336,
    "seen": 3975
  },
  "CMC": {
    "detected": 0,
    "seen": 3970
  },
  "CAT-QuickHeal": {
    "detected": 896,
    "seen": 3975
  },
  "Skyhigh": {
    "detected": 1222,
    "seen": 3973
  },
  "Sangfor": {
    "detected": 2138,
    "seen": 3975
  },
  "Baidu": {
    "detected": 79,
    "seen": 1753
  },
  "Symantec": {
    "detected": 2194,
    "seen": 3975
  },
  "TrendMicro-HouseCall": {
    "detected": 1843,
    "seen": 3975
  },
  "Avast": {
    "detected": 2553,
    "seen": 3974
  },
  "Kaspersky": {
    "detected": 3060,
    "seen": 3974
  },
  "BitDefender": {
    "detected": 2112,
    "seen": 3975
  },
  "Zillya": {
    "detected": 424,
    "seen": 3975
  },
  "TrendMicro": {
    "detected": 1333,
    "seen": 3974
  },
  "Sophos": {
    "detected": 2263,
    "seen": 3975
  },
  "Xcitium": {
    "detected": 305,
    "seen": 3975
  },
  "Avast-Mobile": {
    "detected": 525,
    "seen": 3975
  },
  "Varist": {
    "detected": 2670,
    "seen": 3974
  },
  "VBA32": {
    "detected": 1265,
    "seen": 3975
  },
  "Yandex": {
    "detected": 184,
    "seen": 3975
  },
  "TrellixENS": {
    "detected": 1669,
    "seen": 3957
  },
  "Fortinet": {
    "detected": 2390,
    "seen": 3973
  },
  "AVG": {
    "detected": 2553,
    "seen": 3974
  },
  "Panda": {
    "detected": 931,
    "seen": 3975
  },
  "ClamAV": {
    "detected": 1248,
    "seen": 3975
  },
  "DeepInstinct": {
    "detected": 1805,
    "seen": 3970
  },
  "SymantecMobileInsight": {
    "detected": 0,
    "seen": 3975
  },
  "BitDefenderFalx": {
    "detected": 0,
    "seen": 3975
  },
  "tehtris": {
    "detected": 128,
    "seen": 3975
  },
  "Webroot": {
    "detected": 435,
    "seen": 3975
  },
  "APEX": {
    "detected": 1322,
    "seen": 3975
  },
  "Paloalto": {
    "detected": 1271,
    "seen": 3975
  },
  "Alibaba": {
    "detected": 1121,
    "seen": 3975
  },
  "Trapmine": {
    "detected": 735,
    "seen": 3975
  },
  "Cylance": {
    "detected": 1645,
    "seen": 3975
  },
  "Trustlook": {
    "detected": 0,
    "seen": 3975
  },
  "FireEye": {
    "detected": 15,
    "seen": 15
  },
  "McAfee": {
    "detected": 5,
    "seen": 18
  },
  "BitDefenderTheta": {
    "detected": 2,
    "seen": 2
  },
  "Cyren": {
    "detected": 1,
    "seen": 1
  },
  "McAfee-GW-Edition": {
    "detected": 1,
    "seen": 1
  },
  "MAX": {
    "detected": 2,
    "seen": 2
  },
  "Cybereason": {
    "detected": 0,
    "seen": 1
  }
}