{
  "Lionic": {
    "detected": 632,
    "seen": 1431
  },
  "CTX": {
    "detected": 861,
    "seen": 1431
  },
  "huorong": {
    "detected": 773,
    "seen": 1431
  },
  "VirIT": {
    "detected": 328,
    "seen": 1431
  },
  "ESET-NOD32": {
    "detected": 1116,
    "seen": 1431
  },
  "Cynet": {
    "detected": 915,
    "seen": 1431
  },
  "ViRobot": {
    "detected": 123,
    "seen": 1431
  },
  "F-Secure": {
    "detected": 471,
    "seen": 1431
  },
  "DrWeb": {
    "detected": 610,
    "seen": 1431
  },
  "McAfeeD": {
    "detected": 935,
    "seen": 1431
  },
  "Ikarus": {
    "detected": 940,
    "seen": 1431
  },
  "Avira": {
    "detected": 485,
    "seen": 1431
  },
  "GData": {
    "detected": 891,
    "seen": 1431
  },
  "AhnLab-V3": {
    "detected": 814,
    "seen": 1431
  },
  "TACHYON": {
    "detected": 20,
    "seen": 1431
  },
  "Zoner": {
    "detected": 18,
    "seen": 1431
  },
  "Tencent": {
    "detected": 938,
    "seen": 1431
  },
  "SentinelOne": {
    "detected": 684,
    "seen": 1431
  },
  "alibabacloud": {
    "detected": 743,
    "seen": 1431
  },
  "Bkav": {
    "detected": 597,
    "seen": 1431
  },
  "MicroWorld-eScan": {
    "detected": 836,
    "seen": 1431
  },
  "ALYac": {
    "detected": 531,
    "seen": 999
  },
  "Malwarebytes": {
    "detected": 635,
    "seen": 1431
  },
  "K7AntiVirus": {
    "detected": 520,
    "seen": 1431
  },
  "K7GW": {
    "detected": 535,
    "seen": 1431
  },
  "CrowdStrike": {
    "detected": 655,
    "seen": 1431
  },
  "Microsoft": {
    "detected": 1186,
    "seen": 1431
  },
  "NANO-Antivirus": {
    "detected": 119,
    "seen": 1431
  },
  "Rising": {
    "detected": 988,
    "seen": 1431
  },
  "VIPRE": {
    "detected": 797,
    "seen": 1427
  },
  "Emsisoft": {
    "detected": 832,
    "seen": 1431
  },
  "Jiangmin": {
    "detected": 113,
    "seen": 1431
  },
  "Antiy-AVL": {
    "detected": 852,
    "seen": 1431
  },
  "Kingsoft": {
    "detected": 572,
    "seen": 1431
  },
  "Gridinsoft": {
    "detected": 397,
    "seen": 1431
  },
  "Arcabit": {
    "detected": 821,
    "seen": 1431
  },
  "SUPERAntiSpyware": {
    "detected": 94,
    "seen": 1431
  },
  "ZoneAlarm": {
    "detected": 338,
    "seen": 1431
  },
  "Google": {
    "detected": 1043,
    "seen": 1431
  },
  "Acronis": {
    "detected": 7,
    "seen": 1431
  },
  "MaxSecure": {
    "detected": 591,
    "seen": 1431
  },
  "Elastic": {
    "detected": 826,
    "seen": 1431
  },
  "CMC": {
    "detected": 0,
    "seen": 1431
  },
  "CAT-QuickHeal": {
    "detected": 418,
    "seen": 1431
  },
  "Skyhigh": {
    "detected": 354,
    "seen": 1430
  },
  "Sangfor": {
    "detected": 828,
    "seen": 1431
  },
  "Baidu": {
    "detected": 75,
    "seen": 1431
  },
  "Symantec": {
    "detected": 765,
    "seen": 1431
  },
  "TrendMicro-HouseCall": {
    "detected": 672,
    "seen": 1431
  },
  "Avast": {
    "detected": 867,
    "seen": 1430
  },
  "Kaspersky": {
    "detected": 1077,
    "seen": 1430
  },
  "BitDefender": {
    "detected": 788,
    "seen": 1431
  },
  "Zillya": {
    "detected": 174,
    "seen": 1431
  },
  "TrendMicro": {
    "detected": 447,
    "seen": 1430
  },
  "Sophos": {
    "detected": 825,
    "seen": 1431
  },
  "Xcitium": {
    "detected": 66,
    "seen": 1431
  },
  "Avast-Mobile": {
    "detected": 209,
    "seen": 1431
  },
  "Varist": {
    "detected": 936,
    "seen": 1431
  },
  "VBA32": {
    "detected": 475,
    "seen": 1431
  },
  "Yandex": {
    "detected": 52,
    "seen": 1431
  },
  "TrellixENS": {
    "detected": 554,
    "seen": 1431
  },
  "Fortinet": {
    "detected": 908,
    "seen": 1431
  },
  "AVG": {
    "detected": 867,
    "seen": 1430
  },
  "Panda": {
    "detected": 323,
    "seen": 1431
  },
  "ClamAV": {
    "detected": 485,
    "seen": 1431
  },
  "DeepInstinct": {
    "detected": 729,
    "seen": 1431
  },
  "SymantecMobileInsight": {
    "detected": 0,
    "seen": 1431
  },
  "BitDefenderFalx": {
    "detected": 0,
    "seen": 1431
  },
  "tehtris": {
    "detected": 24,
    "seen": 1431
  },
  "Webroot": {
    "detected": 158,
    "seen": 1431
  },
  "APEX": {
    "detected": 473,
    "seen": 1431
  },
  "Paloalto": {
    "detected": 461,
    "seen": 1431
  },
  "Alibaba": {
    "detected": 422,
    "seen": 1431
  },
  "Trapmine": {
    "detected": 183,
    "seen": 1431
  },
  "Cylance": {
    "detected": 655,
    "seen": 1431
  },
  "Trustlook": {
    "detected": 0,
    "seen": 1431
  }
}