{
  "Lionic": {
    "detected": 966,
    "seen": 2275
  },
  "CTX": {
    "detected": 1338,
    "seen": 2275
  },
  "huorong": {
    "detected": 1232,
    "seen": 2275
  },
  "VirIT": {
    "detected": 508,
    "seen": 2275
  },
  "ESET-NOD32": {
    "detected": 1770,
    "seen": 2275
  },
  "Cynet": {
    "detected": 1407,
    "seen": 2275
  },
  "ViRobot": {
    "detected": 215,
    "seen": 2275
  },
  "F-Secure": {
    "detected": 757,
    "seen": 2275
  },
  "DrWeb": {
    "detected": 1050,
    "seen": 2275
  },
  "McAfeeD": {
    "detected": 1425,
    "seen": 2275
  },
  "Ikarus": {
    "detected": 1516,
    "seen": 2275
  },
  "Avira": {
    "detected": 747,
    "seen": 2275
  },
  "GData": {
    "detected": 1365,
    "seen": 2275
  },
  "AhnLab-V3": {
    "detected": 1220,
    "seen": 2275
  },
  "TACHYON": {
    "detected": 36,
    "seen": 2275
  },
  "Zoner": {
    "detected": 37,
    "seen": 2275
  },
  "Tencent": {
    "detected": 1367,
    "seen": 2095
  },
  "SentinelOne": {
    "detected": 1079,
    "seen": 2275
  },
  "alibabacloud": {
    "detected": 1172,
    "seen": 2275
  },
  "Bkav": {
    "detected": 961,
    "seen": 2244
  },
  "MicroWorld-eScan": {
    "detected": 1295,
    "seen": 2275
  },
  "ALYac": {
    "detected": 939,
    "seen": 1841
  },
  "Malwarebytes": {
    "detected": 957,
    "seen": 2275
  },
  "K7AntiVirus": {
    "detected": 790,
    "seen": 2275
  },
  "K7GW": {
    "detected": 822,
    "seen": 2275
  },
  "CrowdStrike": {
    "detected": 1039,
    "seen": 2275
  },
  "Microsoft": {
    "detected": 1889,
    "seen": 2275
  },
  "NANO-Antivirus": {
    "detected": 185,
    "seen": 2275
  },
  "Rising": {
    "detected": 1577,
    "seen": 2275
  },
  "VIPRE": {
    "detected": 1246,
    "seen": 2271
  },
  "Emsisoft": {
    "detected": 1288,
    "seen": 2275
  },
  "Jiangmin": {
    "detected": 216,
    "seen": 2275
  },
  "Antiy-AVL": {
    "detected": 1350,
    "seen": 2275
  },
  "Kingsoft": {
    "detected": 841,
    "seen": 2275
  },
  "Gridinsoft": {
    "detected": 526,
    "seen": 2275
  },
  "Arcabit": {
    "detected": 1274,
    "seen": 2275
  },
  "SUPERAntiSpyware": {
    "detected": 198,
    "seen": 2275
  },
  "ZoneAlarm": {
    "detected": 532,
    "seen": 2272
  },
  "Google": {
    "detected": 1683,
    "seen": 2275
  },
  "Acronis": {
    "detected": 10,
    "seen": 2275
  },
  "MaxSecure": {
    "detected": 832,
    "seen": 2275
  },
  "Elastic": {
    "detected": 1333,
    "seen": 2275
  },
  "CMC": {
    "detected": 0,
    "seen": 2275
  },
  "CAT-QuickHeal": {
    "detected": 510,
    "seen": 2275
  },
  "Skyhigh": {
    "detected": 642,
    "seen": 2274
  },
  "Sangfor": {
    "detected": 1283,
    "seen": 2275
  },
  "Baidu": {
    "detected": 78,
    "seen": 1712
  },
  "Symantec": {
    "detected": 1276,
    "seen": 2275
  },
  "TrendMicro-HouseCall": {
    "detected": 1054,
    "seen": 2275
  },
  "Avast": {
    "detected": 1416,
    "seen": 2274
  },
  "Kaspersky": {
    "detected": 1728,
    "seen": 2274
  },
  "BitDefender": {
    "detected": 1232,
    "seen": 2275
  },
  "Zillya": {
    "detected": 247,
    "seen": 2275
  },
  "TrendMicro": {
    "detected": 693,
    "seen": 2274
  },
  "Sophos": {
    "detected": 1290,
    "seen": 2275
  },
  "Xcitium": {
    "detected": 99,
    "seen": 2275
  },
  "Avast-Mobile": {
    "detected": 321,
    "seen": 2275
  },
  "Varist": {
    "detected": 1491,
    "seen": 2275
  },
  "VBA32": {
    "detected": 724,
    "seen": 2275
  },
  "Yandex": {
    "detected": 79,
    "seen": 2275
  },
  "TrellixENS": {
    "detected": 909,
    "seen": 2272
  },
  "Fortinet": {
    "detected": 1384,
    "seen": 2275
  },
  "AVG": {
    "detected": 1416,
    "seen": 2274
  },
  "Panda": {
    "detected": 486,
    "seen": 2275
  },
  "ClamAV": {
    "detected": 704,
    "seen": 2275
  },
  "DeepInstinct": {
    "detected": 1095,
    "seen": 2275
  },
  "SymantecMobileInsight": {
    "detected": 0,
    "seen": 2275
  },
  "BitDefenderFalx": {
    "detected": 0,
    "seen": 2275
  },
  "tehtris": {
    "detected": 48,
    "seen": 2275
  },
  "Webroot": {
    "detected": 193,
    "seen": 2275
  },
  "APEX": {
    "detected": 718,
    "seen": 2275
  },
  "Paloalto": {
    "detected": 749,
    "seen": 2275
  },
  "Alibaba": {
    "detected": 654,
    "seen": 2275
  },
  "Trapmine": {
    "detected": 307,
    "seen": 2275
  },
  "Cylance": {
    "detected": 990,
    "seen": 2275
  },
  "Trustlook": {
    "detected": 0,
    "seen": 2275
  },
  "FireEye": {
    "detected": 3,
    "seen": 3
  },
  "McAfee": {
    "detected": 0,
    "seen": 3
  }
}